qa_engine/__init__.py
qa_engine/qa_engine.py
qa_engine/config/__init__.py
qa_engine/config/config.py
qa_engine/prompt/__init__.py
qa_engine/prompt/prompt.py
qa_engine/utils/__init__.py
qa_engine/utils/chatgpt.py
qa_engine-0.0.1.dist-info/METADATA
qa_engine-0.0.1.dist-info/WHEEL
qa_engine-0.0.1.dist-info/licenses/LICENSE
qa_engine-0.0.1.dist-info/RECORD
