Metadata-Version: 2.1
Name: qa_engine
Version: 0.0.1
Summary: OMbot QA Engine
Project-URL: Homepage, https://git.linker.cc/research/misc/qa_engine.git
Author-email: KeleiJiang <18852088031@gmail.com>
License-File: LICENSE
Classifier: License :: OSI Approved :: MIT License
Classifier: Operating System :: OS Independent
Classifier: Programming Language :: Python :: 3
Requires-Python: >=3.7
Requires-Dist: langchain>=0.0.142
